PharmaPy/.DS_Store
PharmaPy/__init__.py
PharmaPy/request.py
pharmapy-0.0.2.dist-info/METADATA
pharmapy-0.0.2.dist-info/WHEEL
pharmapy-0.0.2.dist-info/licenses/LICENSE
pharmapy-0.0.2.dist-info/RECORD
